netsuitesdk/__init__.py
netsuitesdk/connection.py
netsuitesdk/api/__init__.py
netsuitesdk/api/accounts.py
netsuitesdk/api/adv_inter_company_journal_entries.py
netsuitesdk/api/base.py
netsuitesdk/api/billing_account.py
netsuitesdk/api/classifications.py
netsuitesdk/api/credit_memos.py
netsuitesdk/api/currencies.py
netsuitesdk/api/custom_lists.py
netsuitesdk/api/custom_record_types.py
netsuitesdk/api/custom_records.py
netsuitesdk/api/custom_segments.py
netsuitesdk/api/customers.py
netsuitesdk/api/departments.py
netsuitesdk/api/employees.py
netsuitesdk/api/expense_categories.py
netsuitesdk/api/expense_reports.py
netsuitesdk/api/files.py
netsuitesdk/api/folders.py
netsuitesdk/api/invoices.py
netsuitesdk/api/items.py
netsuitesdk/api/journal_entries.py
netsuitesdk/api/locations.py
netsuitesdk/api/price_level.py
netsuitesdk/api/projects.py
netsuitesdk/api/subsidiaries.py
netsuitesdk/api/tax_groups.py
netsuitesdk/api/tax_items.py
netsuitesdk/api/terms.py
netsuitesdk/api/usage.py
netsuitesdk/api/vendor_bills.py
netsuitesdk/api/vendor_credits.py
netsuitesdk/api/vendor_payments.py
netsuitesdk/api/vendors.py
netsuitesdk/errors/__init__.py
netsuitesdk/errors/errors.py
netsuitesdk/errors/helpers.py
netsuitesdk/errors/parser.py
netsuitesdk/internal/__init__.py
netsuitesdk/internal/client.py
netsuitesdk/internal/constants.py
netsuitesdk/internal/exceptions.py
netsuitesdk/internal/netsuite_types.py
netsuitesdk/internal/utils.py
netsuitesdk-3.1.2.dist-info/licenses/LICENSE
netsuitesdk-3.1.2.dist-info/METADATA
netsuitesdk-3.1.2.dist-info/WHEEL
netsuitesdk-3.1.2.dist-info/top_level.txt
netsuitesdk-3.1.2.dist-info/RECORD
