Metadata-Version: 2.4
Name: netsuitesdk
Version: 3.1.2
Summary: Python SDK for accessing the NetSuite SOAP webservice
Home-page: https://github.com/fylein/netsuite-sdk-py
Author: Siva Narayanan
Author-email: siva@fyle.in
License: MIT
Keywords: netsuite,api,python,sdk
Classifier: Topic :: Internet :: WWW/HTTP
Classifier: Intended Audience :: Developers
Classifier: Programming Language :: Python :: 3
Classifier: License :: OSI Approved :: MIT License
Classifier: Operating System :: OS Independent
License-File: LICENSE
Requires-Dist: zeep
Dynamic: author
Dynamic: author-email
Dynamic: classifier
Dynamic: description
Dynamic: description-content-type
Dynamic: home-page
Dynamic: keywords
Dynamic: license
Dynamic: license-file
Dynamic: requires-dist
Dynamic: summary
